{
  "openapi": "3.0.3",
  "info": {
    "title": "OpenAPI definition",
    "version": "v0"
  },
  "tags": [
    {
      "name": "declarationsConsolideesAlmerys"
    }
  ],
  "paths": {},
  "components": {
    "schemas": {
      "DeclarationsConsolideesAlmerys": {
        "type": "object",
        "additionalProperties": false,
        "properties": {
          "codeEtat": {
            "type": "string"
          },
          "effetDebut": {
            "type": "string",
            "format": "date-time"
          },
          "idDeclarant": {
            "type": "string"
          },
          "isCarteTPaEditer": {
            "type": "boolean"
          },
          "dateCreation": {
            "type": "string",
            "format": "date-time"
          },
          "userCreation": {
            "type": "string"
          },
          "dateModification": {
            "type": "string",
            "format": "date-time"
          },
          "userModification": {
            "type": "string"
          },
          "beneficiaire": {
            "$ref": "/commons-schema-openapi.json#/components/schemas/Beneficiaire"
          },
          "contrat": {
            "$ref": "/commons-schema-openapi.json#/components/schemas/Contrat"
          },
          "domaineDroits": {
            "$ref": "/commons-schema-openapi.json#/components/schemas/DomaineDroit"
          },
          "codeService": {
            "type": "string"
          },
          "AMC_contrat_CSD": {
            "type": "string"
          },
          "idDeclarations": {
            "type": "array",
			"items": {
			  "type": "string"
			}
          },
          "dateConsolidation": {
            "type": "string",
            "format": "date-time"
          },
          "_id": {
            "type": "string"
          }
        },
        "required": [],
        "title": "DeclarationsConsolideesAlmerys"
      }
    }
  }
}
